algoplay/__init__.py
algoplay/color.py
algoplay/exceptions.py
algoplay/keypress.py
algoplay/play.py
algo_play-0.0.25.dist-info/METADATA
algo_play-0.0.25.dist-info/WHEEL
algo_play-0.0.25.dist-info/top_level.txt
algo_play-0.0.25.dist-info/RECORD
