Metadata-Version: 2.1
Name: algo-play
Version: 0.0.25
Summary: The easiest way to make games and media projects in Python.
Home-page: https://github.com/replit/play
Author: Repl.it
Author-email: gchiacchieri@gmail.com
Maintainer: chamik
Maintainer-email: code@chamik.eu
License: MIT
Classifier: License :: OSI Approved :: MIT License
Classifier: Programming Language :: Python :: 3
Classifier: Programming Language :: Python :: 3.7
Requires-Python: >=3.5
Requires-Dist: pygame
Requires-Dist: numpy
Requires-Dist: pymunk
